jx3apifun/__init__.py
jx3apifun/const.py
jx3apifun/exceptions.py
jx3apifun/interface.py
jx3apifun/interface_async.py
jx3apifun/jx3api.py
jx3apifun/logger.py
jx3apifun/model.py
jx3apifun/permission.py
jx3apifun/http/__init__.py
jx3apifun/http/caller.py
jx3apifun/http/driver.py
jx3apifun/http/handler.py
jx3apifun/websocket/__init__.py
jx3apifun/websocket/caller.py
jx3apifun/websocket/collator.py
jx3apifun/websocket/driver.py
jx3apifun/websocket/event.py
jx3apifun/websocket/handler.py
jx3apifun/websocket/register.py
jx3apifun/websocket/store.py
jx3apifun-0.0.4.dist-info/LICENSE
jx3apifun-0.0.4.dist-info/METADATA
jx3apifun-0.0.4.dist-info/WHEEL
jx3apifun-0.0.4.dist-info/top_level.txt
jx3apifun-0.0.4.dist-info/RECORD
