Metadata-Version: 2.1
Name: jx3apifun
Version: 0.0.4
Summary: 女生自用jx3api sdk for python
Home-page: https://github.com/JX3API/jx3api-fun-py
Author: JustUndertaker
Author-email: 806792561@qq.com
Classifier: Programming Language :: Python :: 3.9
Classifier: Programming Language :: Python :: 3.10
Classifier: Programming Language :: Python :: 3.11
Classifier: Programming Language :: Python :: 3.12
Classifier: License :: OSI Approved :: MIT License
Requires-Python: >=3.9
License-File: LICENSE
